jupyter_flex/__about__.py
jupyter_flex/__init__.py
jupyter_flex/config.py
jupyter_flex/exporter.py
jupyter_flex/exporter_illusionist.py
jupyter_flex/tests/__init__.py
jupyter_flex/tests/conftest.py
jupyter_flex/tests/test_examples.py
jupyter_flex/tests/test_illusionist.py
jupyter_flex/tests/test_layouts.py
jupyter_flex/tests/test_pkg.py
jupyter_flex/tests/test_splinter.py
jupyter_flex-0.9.1.data/data/share/jupyter/nbconvert/templates/flex/conf.json
jupyter_flex-0.9.1.data/data/share/jupyter/nbconvert/templates/flex/flex.j2
jupyter_flex-0.9.1.data/data/share/jupyter/nbconvert/templates/flex/index.html.j2
jupyter_flex-0.9.1.data/data/share/jupyter/nbconvert/templates/flex/static/.gitignore
jupyter_flex-0.9.1.data/data/share/jupyter/nbconvert/templates/flex/static/213a070ccb5dfb80f3b1.svg
jupyter_flex-0.9.1.data/data/share/jupyter/nbconvert/templates/flex/static/3c5f86a14ac61c80f6af.eot
jupyter_flex-0.9.1.data/data/share/jupyter/nbconvert/templates/flex/static/64.jupyter-flex-embed.js
jupyter_flex-0.9.1.data/data/share/jupyter/nbconvert/templates/flex/static/64.jupyter-flex-embed.js.map
jupyter_flex-0.9.1.data/data/share/jupyter/nbconvert/templates/flex/static/7a065a1c0cb2d586cecb.woff
jupyter_flex-0.9.1.data/data/share/jupyter/nbconvert/templates/flex/static/7d6ec71e2466a9fd777f.woff2
jupyter_flex-0.9.1.data/data/share/jupyter/nbconvert/templates/flex/static/87.jupyter-flex-embed.js
jupyter_flex-0.9.1.data/data/share/jupyter/nbconvert/templates/flex/static/87.jupyter-flex-embed.js.map
jupyter_flex-0.9.1.data/data/share/jupyter/nbconvert/templates/flex/static/d4cbe6fb154cf9e9036c.ttf
jupyter_flex-0.9.1.data/data/share/jupyter/nbconvert/templates/flex/static/favicon.png
jupyter_flex-0.9.1.data/data/share/jupyter/nbconvert/templates/flex/static/jupyter-flex-embed.css
jupyter_flex-0.9.1.data/data/share/jupyter/nbconvert/templates/flex/static/jupyter-flex-embed.css.map
jupyter_flex-0.9.1.data/data/share/jupyter/nbconvert/templates/flex/static/jupyter-flex-embed.js
jupyter_flex-0.9.1.dist-info/METADATA
jupyter_flex-0.9.1.dist-info/WHEEL
jupyter_flex-0.9.1.dist-info/entry_points.txt
jupyter_flex-0.9.1.dist-info/RECORD
