Metadata-Version: 2.1
Name: jupyter-flex
Version: 0.9.1
Summary: Build dashboards using Jupyter Notebooks
Project-URL: homepage, https://github.com/danielfrg/jupyter-flex
Project-URL: repository, https://github.com/danielfrg/jupyter-flex
Project-URL: documentation, https://github.com/danielfrg/jupyter-flex
Author-email: Daniel Rodriguez <daniel@danielfrg.com>
Maintainer-email: Daniel Rodriguez <daniel@danielfrg.com>
License-Expression: Apache-2.0
Keywords: dashboards,jupyter,jupyterlab,notebooks,voila
Classifier: Development Status :: 5 - Production/Stable
Classifier: Intended Audience :: Developers
Classifier: Intended Audience :: Science/Research
Classifier: Operating System :: OS Independent
Classifier: Programming Language :: Python
Classifier: Programming Language :: Python :: 3.8
Classifier: Programming Language :: Python :: 3.9
Classifier: Programming Language :: Python :: 3.10
Classifier: Programming Language :: Python :: 3.11
Classifier: Programming Language :: Python :: Implementation :: CPython
Classifier: Topic :: Scientific/Engineering
Requires-Python: >=3.8
Requires-Dist: ipykernel>=6.21.3
Requires-Dist: jinja2>=3.1.2
Requires-Dist: markupsafe>=2.0.1
Requires-Dist: nbconvert>=7.2.9
Requires-Dist: voila>=0.4.0
Provides-Extra: docs
Requires-Dist: mkdocs; extra == 'docs'
Requires-Dist: mkdocs-jupyter>=0.23.0; extra == 'docs'
Requires-Dist: mkdocs-material; extra == 'docs'
Requires-Dist: mkdocs-minify-plugin; extra == 'docs'
Requires-Dist: pygments; extra == 'docs'
Requires-Dist: pymdown-extensions; extra == 'docs'
Provides-Extra: test
Requires-Dist: coverage[toml]; extra == 'test'
Requires-Dist: pytest; extra == 'test'
Requires-Dist: pytest-cov; extra == 'test'
Requires-Dist: pytest-html; extra == 'test'
Requires-Dist: pytest-image-diff; extra == 'test'
Requires-Dist: pytest-selenium; extra == 'test'
Requires-Dist: pytest-splinter; extra == 'test'
